kiara_plugin/service/__init__.py
kiara_plugin/service/data_types.py
kiara_plugin/service/defaults.py
kiara_plugin/service/models.py
kiara_plugin/service/py.typed
kiara_plugin/service/version.txt
kiara_plugin/service/interfaces/__init__.py
kiara_plugin/service/interfaces/cli/__init__.py
kiara_plugin/service/interfaces/cli/service/__init__.py
kiara_plugin/service/interfaces/cli/service/commands.py
kiara_plugin/service/modules/__init__.py
kiara_plugin/service/openapi/__init__.py
kiara_plugin/service/openapi/service.py
kiara_plugin/service/openapi/controllers/__init__.py
kiara_plugin/service/openapi/controllers/context_info.py
kiara_plugin/service/openapi/controllers/jobs.py
kiara_plugin/service/openapi/controllers/modules.py
kiara_plugin/service/openapi/controllers/operations.py
kiara_plugin/service/openapi/controllers/pipeline.py
kiara_plugin/service/openapi/controllers/render.py
kiara_plugin/service/openapi/controllers/values.py
kiara_plugin/service/openapi/controllers/workflows.py
kiara_plugin/service/pipelines/.gitkeep
kiara_plugin/service/pipelines/__init__.py
kiara_plugin/service/resources/.gitkeep
kiara_plugin/service/resources/static/custom.css
kiara_plugin/service/resources/static/favicon.ico
kiara_plugin/service/resources/static/input.css
kiara_plugin/service/resources/static/main.css
kiara_plugin/service/resources/static/simple.css
kiara_plugin/service/resources/templates/base.html
kiara_plugin/service/resources/templates/index.html
kiara_plugin/service/resources/templates/macros.html
kiara_plugin/service/resources/templates/jobs/job_finished.html
kiara_plugin/service/resources/templates/jobs/job_monitor.html
kiara_plugin/service/resources/templates/operations/index.html
kiara_plugin/service/resources/templates/operations/operation_view.html
kiara_plugin/service/resources/templates/operations/operations.html
kiara_plugin/service/resources/templates/values/index.html
kiara_plugin/service/resources/templates/values/value_inputs_form.html
kiara_plugin.service-0.4.7.dist-info/AUTHORS.md
kiara_plugin.service-0.4.7.dist-info/LICENSE
kiara_plugin.service-0.4.7.dist-info/METADATA
kiara_plugin.service-0.4.7.dist-info/WHEEL
kiara_plugin.service-0.4.7.dist-info/entry_points.txt
kiara_plugin.service-0.4.7.dist-info/top_level.txt
kiara_plugin.service-0.4.7.dist-info/RECORD
