Metadata-Version: 2.1
Name: kiara-plugin.service
Version: 0.4.7
Summary: A plugin to create, run and manage a service for kiara functionality.
Author-email: Markus Binsteiner <markus@frkl.io>
License: MPL-2.0
Project-URL: homepage, https://github.com/DHARPA-Project/kiara_plugin.service
Project-URL: documentation, https://DHARPA-Project.github.io/kiara_plugin.service
Project-URL: repository, https://github.com/DHARPA-Project/kiara_plugin.service
Keywords: kiara
Classifier: Programming Language :: Python :: 3
Classifier: Development Status :: 3 - Alpha
Classifier: License :: OSI Approved :: Mozilla Public License 2.0 (MPL 2.0)
Classifier: Programming Language :: Python
Classifier: Programming Language :: Python :: 3
Classifier: Programming Language :: Python :: 3 :: Only
Classifier: Programming Language :: Python :: 3.8
Classifier: Programming Language :: Python :: 3.9
Classifier: Programming Language :: Python :: 3.10
Classifier: Programming Language :: Python :: 3.11
Requires-Python: >=3.8
License-File: LICENSE
License-File: AUTHORS.md
Requires-Dist: kiara (>=0.4.49)
Requires-Dist: kiara-plugin.core-types (>=0.4.20)
Requires-Dist: uvicorn (>=0.22.0)
Requires-Dist: starlite (==1.39.0)
Provides-Extra: all
Provides-Extra: all_dev
Provides-Extra: dev_all
Requires-Dist: kiara[dev_all] ; extra == 'dev_all'
Provides-Extra: dev_documentation
Requires-Dist: kiara[dev_documentation] ; extra == 'dev_documentation'
Provides-Extra: dev_testing
Requires-Dist: kiara[dev_testing] ; extra == 'dev_testing'
Provides-Extra: dev_utils
Requires-Dist: kiara[dev_utils] ; extra == 'dev_utils'
Provides-Extra: streamlit
Requires-Dist: kiara-plugin.streamlit ; extra == 'streamlit'
